Metadata-Version: 1.0
Name: nife-distribution
Version: 1.2
Summary: Gaussian and Binomial  distributions
Home-page: UNKNOWN
Author: Nifesimi Ademoye
Author-email: nifesimifrank@gmail.com
License: UNKNOWN
Platform: UNKNOWN
